{
  "registered": [
    {
      "name": "1",
      "email": "1@gmail.com",
      "registeredAt": "2026-01-12T22:47:27.441Z"
    },
    {
      "name": "2",
      "email": "2@gmail.com",
      "registeredAt": "2026-01-12T22:47:28.985Z"
    },
    {
      "name": "3",
      "email": "3@gmail.com",
      "registeredAt": "2026-01-12T22:47:30.534Z"
    },
    {
      "name": "4",
      "email": "4@gmail.com",
      "registeredAt": "2026-01-12T22:47:32.117Z"
    },
    {
      "name": "5",
      "email": "5@gmail.com",
      "registeredAt": "2026-01-12T22:47:33.659Z"
    },
    {
      "name": "6",
      "email": "6@gmail.com",
      "registeredAt": "2026-01-12T22:47:35.230Z"
    },
    {
      "name": "7",
      "email": "7@gmail.com",
      "registeredAt": "2026-01-12T22:47:36.780Z"
    },
    {
      "name": "8",
      "email": "8@gmail.com",
      "registeredAt": "2026-01-12T22:47:38.349Z"
    },
    {
      "name": "9",
      "email": "9@gmail.com",
      "registeredAt": "2026-01-12T22:47:39.903Z"
    },
    {
      "name": "10",
      "email": "10@gmail.com",
      "registeredAt": "2026-01-12T22:47:41.449Z"
    },
    {
      "name": "11",
      "email": "11@gmail.com",
      "registeredAt": "2026-01-12T22:47:42.992Z"
    },
    {
      "name": "12",
      "email": "12@gmail.com",
      "registeredAt": "2026-01-12T22:47:44.563Z"
    },
    {
      "name": "13",
      "email": "13@gmail.com",
      "registeredAt": "2026-01-12T22:47:46.107Z"
    },
    {
      "name": "14",
      "email": "14@gmail.com",
      "registeredAt": "2026-01-12T22:47:47.658Z"
    },
    {
      "name": "15",
      "email": "15@gmail.com",
      "registeredAt": "2026-01-12T22:47:49.208Z"
    },
    {
      "name": "16",
      "email": "16@gmail.com",
      "registeredAt": "2026-01-12T22:47:50.769Z"
    },
    {
      "name": "17",
      "email": "17@gmail.com",
      "registeredAt": "2026-01-12T22:47:52.334Z"
    },
    {
      "name": "18",
      "email": "18@gmail.com",
      "registeredAt": "2026-01-12T22:47:53.872Z"
    },
    {
      "name": "19",
      "email": "19@gmail.com",
      "registeredAt": "2026-01-12T22:47:55.435Z"
    },
    {
      "name": "20",
      "email": "20@gmail.com",
      "registeredAt": "2026-01-12T22:47:56.975Z"
    },
    {
      "name": "21",
      "email": "21@gmail.com",
      "registeredAt": "2026-01-12T22:47:58.550Z"
    },
    {
      "name": "22",
      "email": "22@gmail.com",
      "registeredAt": "2026-01-12T22:48:00.092Z"
    },
    {
      "name": "23",
      "email": "23@gmail.com",
      "registeredAt": "2026-01-12T22:48:01.642Z"
    },
    {
      "name": "24",
      "email": "24@gmail.com",
      "registeredAt": "2026-01-12T22:48:03.209Z"
    }
  ],
  "waitlist": []
}